tkinter_a11y_lint/__init__.py
tkinter_a11y_lint/plugin.py
tkinter_a11y_lint-0.1.0.dist-info/licenses/LICENSE
tkinter_a11y_lint-0.1.0.dist-info/METADATA
tkinter_a11y_lint-0.1.0.dist-info/WHEEL
tkinter_a11y_lint-0.1.0.dist-info/entry_points.txt
tkinter_a11y_lint-0.1.0.dist-info/top_level.txt
tkinter_a11y_lint-0.1.0.dist-info/RECORD
