Metadata-Version: 2.4
Name: tkinter-a11y-lint
Version: 0.1.0
Summary: A pylint plugin for tkinter accessibility linting
Author-email: Anthony Shaw <your.email@example.com>
License: MIT
Project-URL: Homepage, https://github.com/tonybaloney/tkinter-a11y-lint
Project-URL: Repository, https://github.com/tonybaloney/tkinter-a11y-lint
Project-URL: Issues, https://github.com/tonybaloney/tkinter-a11y-lint/issues
Classifier: Development Status :: 3 - Alpha
Classifier: Intended Audience :: Developers
Classifier: License :: OSI Approved :: MIT License
Classifier: Operating System :: OS Independent
Classifier: Programming Language :: Python :: 3
Classifier: Programming Language :: Python :: 3.8
Classifier: Programming Language :: Python :: 3.9
Classifier: Programming Language :: Python :: 3.10
Classifier: Programming Language :: Python :: 3.11
Classifier: Programming Language :: Python :: 3.12
Classifier: Programming Language :: Python :: 3.13
Classifier: Topic :: Software Development :: Quality Assurance
Requires-Python: >=3.8
License-File: LICENSE
Requires-Dist: pylint>=2.15.0
Provides-Extra: dev
Requires-Dist: pytest>=7.0.0; extra == "dev"
Requires-Dist: pytest-cov>=4.0.0; extra == "dev"
Requires-Dist: flake8>=5.0.0; extra == "dev"
Dynamic: license-file
